darkfield_cli/__init__.py
darkfield_cli/api_client.py
darkfield_cli/auth_utils.py
darkfield_cli/config.py
darkfield_cli/errors.py
darkfield_cli/main.py
darkfield_cli/commands/__init__.py
darkfield_cli/commands/analyze.py
darkfield_cli/commands/auth.py
darkfield_cli/commands/benchmarks.py
darkfield_cli/commands/billing.py
darkfield_cli/commands/experiments.py
darkfield_cli/commands/extract.py
darkfield_cli/commands/keys.py
darkfield_cli/commands/monitor.py
darkfield_cli/commands/persona.py
darkfield_cli/utils/__init__.py
darkfield_cli/utils/batch_processor.py
darkfield_cli/utils/file_handlers.py
darkfield_cli/utils/llm_service.py
darkfield_cli/utils/persona_manager.py
darkfield_cli-0.2.3.dist-info/licenses/LICENSE
darkfield_cli-0.2.3.dist-info/METADATA
darkfield_cli-0.2.3.dist-info/WHEEL
darkfield_cli-0.2.3.dist-info/entry_points.txt
darkfield_cli-0.2.3.dist-info/top_level.txt
darkfield_cli-0.2.3.dist-info/RECORD
