Metadata-Version: 2.4
Name: darkfield-cli
Version: 0.2.3
Summary: Navigate the topology of mind - ML safety through persona vectors
Home-page: https://github.com/darkfield-ai/darkfield-cli
Author: Darkfield AI
Author-email: darkfield <contact@darkfield.ai>
License: MIT
Project-URL: Homepage, https://darkfield.ai
Project-URL: Documentation, https://darkfield.ai/docs
Project-URL: Repository, https://github.com/darkfield-ai/cli
Project-URL: Issues, https://github.com/darkfield-ai/cli/issues
Keywords: ai,ml,safety,persona-vectors,alignment
Classifier: Development Status :: 3 - Alpha
Classifier: Intended Audience :: Developers
Classifier: License :: OSI Approved :: MIT License
Classifier: Programming Language :: Python :: 3
Classifier: Programming Language :: Python :: 3.11
Classifier: Programming Language :: Python :: 3.12
Classifier: Topic :: Scientific/Engineering :: Artificial Intelligence
Requires-Python: >=3.8
License-File: LICENSE
Requires-Dist: click>=8.0
Requires-Dist: requests>=2.28
Requires-Dist: rich>=13.0
Requires-Dist: pydantic>=2.0
Requires-Dist: python-dotenv>=1.0
Requires-Dist: keyring>=24.0
Requires-Dist: tabulate>=0.9
Requires-Dist: tqdm>=4.65
Requires-Dist: websocket-client>=1.5
Requires-Dist: numpy>=1.24.0
Requires-Dist: PyYAML>=6.0
Requires-Dist: pandas>=2.0
Requires-Dist: chardet>=5.0
Requires-Dist: tenacity>=8.0
Dynamic: author
Dynamic: home-page
Dynamic: license-file
Dynamic: requires-python
